edgy.event-0.1.10-py3.6-nspkg.pth
edgy/event/__init__.py
edgy/event/_version.py
edgy/event/dispatcher.py
edgy/event/event.py
edgy.event-0.1.10.dist-info/DESCRIPTION.rst
edgy.event-0.1.10.dist-info/METADATA
edgy.event-0.1.10.dist-info/RECORD
edgy.event-0.1.10.dist-info/WHEEL
edgy.event-0.1.10.dist-info/metadata.json
edgy.event-0.1.10.dist-info/namespace_packages.txt
edgy.event-0.1.10.dist-info/top_level.txt
