Metadata-Version: 2.0
Name: edgy.event
Version: 0.1.10
Summary: Event dispatcher
Home-page: https://github.com/python-edgy/event
Author: UNKNOWN
Author-email: UNKNOWN
License: Apache License, Version 2.0
Download-URL: https://github.com/python-edgy/event/tarball/0.1.10
Platform: UNKNOWN
Provides-Extra: dev
Requires-Dist: coverage (<4.3,>=4.2); extra == 'dev'
Requires-Dist: mock (>=2.0,<2.1); extra == 'dev'
Requires-Dist: nose (>=1.3,<1.4); extra == 'dev'
Requires-Dist: pylint (>=1.6,<1.7); extra == 'dev'
Requires-Dist: pytest (<3.1,>=3.0); extra == 'dev'
Requires-Dist: pytest-cov (<2.4,>=2.3); extra == 'dev'
Requires-Dist: sphinx; extra == 'dev'
Requires-Dist: sphinx-rtd-theme; extra == 'dev'
Requires-Dist: yapf; extra == 'dev'
